[
  {
    "title": "VVIP Tee — Black",
    "image": "/shoppe/assets/tee-black.jpg",
    "description": "Heavyweight cotton tee with front logo.",
    "price": 30,
    "currency": "USD",
    "url": "https://your-checkout.example/tee-black",
    "available": true,
    "tags": ["#tee", "#apparel"]
  },
  {
    "title": "Sticker Pack (15)",
    "image": "/shoppe/assets/stickers.jpg",
    "description": "Advertise your VVIP.",
    "price": 20,
    "currency": "USD",
    "url": "https://your-checkout.example/poster",
    "available": true,
    "tags": ["#poster", "#print"]
  },
  {
    "title": "Cassette — Unlimited",
    "image": "/shoppe/assets/cassette.jpg",
    "description": "Edition of 100. Includes download code.",
    "price": 12,
    "currency": "USD",
    "url": "https://your-checkout.example/cassette",
    "available": false,
    "tags": ["#cassette", "#audio"]
  }
]